sphinx_revealjs_slides/__init__.py
sphinx_revealjs_slides/builder.py
sphinx_revealjs_slides/directives/__init__.py
sphinx_revealjs_slides/directives/_base_slide.py
sphinx_revealjs_slides/directives/incremental.py
sphinx_revealjs_slides/directives/newslide.py
sphinx_revealjs_slides/directives/speakernote.py
sphinx_revealjs_slides/overridenodes.py
sphinx_revealjs_slides/themes/lib/reveal.js/dist/reset.css
sphinx_revealjs_slides/themes/lib/reveal.js/dist/reveal.css
sphinx_revealjs_slides/themes/lib/reveal.js/dist/reveal.esm.js
sphinx_revealjs_slides/themes/lib/reveal.js/dist/reveal.esm.js.map
sphinx_revealjs_slides/themes/lib/reveal.js/dist/reveal.js
sphinx_revealjs_slides/themes/lib/reveal.js/dist/reveal.js.map
sphinx_revealjs_slides/themes/lib/reveal.js/dist/theme/beige.css
sphinx_revealjs_slides/themes/lib/reveal.js/dist/theme/black-contrast.css
sphinx_revealjs_slides/themes/lib/reveal.js/dist/theme/black.css
sphinx_revealjs_slides/themes/lib/reveal.js/dist/theme/blood.css
sphinx_revealjs_slides/themes/lib/reveal.js/dist/theme/dracula.css
sphinx_revealjs_slides/themes/lib/reveal.js/dist/theme/fonts/league-gothic/LICENSE
sphinx_revealjs_slides/themes/lib/reveal.js/dist/theme/fonts/league-gothic/league-gothic.css
sphinx_revealjs_slides/themes/lib/reveal.js/dist/theme/fonts/league-gothic/league-gothic.eot
sphinx_revealjs_slides/themes/lib/reveal.js/dist/theme/fonts/league-gothic/league-gothic.ttf
sphinx_revealjs_slides/themes/lib/reveal.js/dist/theme/fonts/league-gothic/league-gothic.woff
sphinx_revealjs_slides/themes/lib/reveal.js/dist/theme/fonts/source-sans-pro/LICENSE
sphinx_revealjs_slides/themes/lib/reveal.js/dist/theme/fonts/source-sans-pro/source-sans-pro-italic.eot
sphinx_revealjs_slides/themes/lib/reveal.js/dist/theme/fonts/source-sans-pro/source-sans-pro-italic.ttf
sphinx_revealjs_slides/themes/lib/reveal.js/dist/theme/fonts/source-sans-pro/source-sans-pro-italic.woff
sphinx_revealjs_slides-0.2.6.dist-info/METADATA
sphinx_revealjs_slides-0.2.6.dist-info/WHEEL
sphinx_revealjs_slides-0.2.6.dist-info/RECORD
