Metadata-Version: 2.1
Name: sphinx-revealjs-slides
Version: 0.2.6
Summary: 
Author: Ashley Trinh
Author-email: ashley@hackbrightacademy.com
Requires-Python: >=3.9,<4.0
Classifier: Programming Language :: Python :: 3
Classifier: Programming Language :: Python :: 3.9
Classifier: Programming Language :: Python :: 3.10
Classifier: Programming Language :: Python :: 3.11
Requires-Dist: sphinx (>=6,<8)
